pyGSLModel/GSL_score.py
pyGSLModel/__init__.py
pyGSLModel/model_analysis.py
pyGSLModel/model_preparation.py
pyGSLModel/transcriptomic_integration.py
pygslmodel-1.0.0.dist-info/licenses/LICENSE
pygslmodel-1.0.0.dist-info/METADATA
pygslmodel-1.0.0.dist-info/WHEEL
pygslmodel-1.0.0.dist-info/top_level.txt
pygslmodel-1.0.0.dist-info/RECORD
