Metadata-Version: 2.4
Name: pyGSLModel
Version: 1.0.0
Summary: A python package for modeling GSL metabolism and performing transcriptomic integration
Home-page: https://github.com/JackWJW/pyGSLModel
Author: Jack Welland
License: GNU
Requires-Python: >=3.10
License-File: LICENSE
Requires-Dist: requests
Requires-Dist: cobra
Requires-Dist: pyfastcore
Requires-Dist: mygene
Requires-Dist: pandas
Requires-Dist: matplotlib
Requires-Dist: seaborn
Requires-Dist: imatpy
Requires-Dist: numpy
Requires-Dist: huggingface_hub
Requires-Dist: joblib
Requires-Dist: tqdm
Requires-Dist: scikit-learn
Requires-Dist: skorch
Requires-Dist: scipy
Requires-Dist: torch
Requires-Dist: pyvis
Dynamic: author
Dynamic: description
Dynamic: description-content-type
Dynamic: home-page
Dynamic: license
Dynamic: license-file
Dynamic: requires-dist
Dynamic: requires-python
Dynamic: summary
